{"simplified":"区域","traditional":"區域","pinyin":"qū yù","definitions":[{"partsOfSpeech":"noun","meaning":"area","sentences":[{"simplifiedText":"这是一个大区域。","traditionalText":"這是一個大區域。","pinyin":"zhè shì yī gè dà qū yù.","translation":"This is a large area.","audioPath":"/Users/johnwu/code/anki_experiment/chinese-app-prototype/.data/db/audio/823e81b9d95e1453307c906237ff178f.mp3","voiceName":"zh-CN-XiaozhenNeural","tags":["EASY_TO_USE"]},{"simplifiedText":"考虑到该区域的多样性，我们需要为每个子区域制定特定的规划。","traditionalText":"考慮到該區域的多樣性，我們需要為每個子區域制定特定的規劃。","pinyin":"kǎo lǜ dào gāi qū yù de duō yàng xìng, wǒ men xū yào wèi měi gè zǐ qū yù zhì dìng tè dìng de guī huà.","translation":"Considering the diversity of the area, we need to make specific plans for each sub-area.","audioPath":"zh-CN-XiaoxiaoNeural","voiceName":"/Users/johnwu/code/anki_experiment/chinese-app-prototype/.data/db/audio/f02e9bada06048fcfeae26a380225575.mp3","tags":["INVOLVED"]}]},{"partsOfSpeech":"Noun","meaning":"district","sentences":[{"simplifiedText":"这个区域很美。","traditionalText":"這個區域很美。","pinyin":"Zhège qūyù hěn měi.","translation":"This district is very beautiful.","audioPath":"/Users/johnwu/code/anki_experiment/chinese-app-prototype/.data/db/audio/90bc46cdebce1d68392dc339605e856f.mp3","voiceName":"zh-CN-YunyeNeural","tags":["EASY_TO_USE"]},{"simplifiedText":"虽然这个区域经济条件较差，但人们都非常友好。","traditionalText":"雖然這個區域經濟條件較差，但人們都非常友好。","pinyin":"Suīrán zhège qūyù jīngjì tiáojiàn jiào chà, dàn rénmen dōu fēicháng yǒuhǎo.","translation":"Although the economic conditions in this district are poor, the people are very friendly.","audioPath":"zh-CN-YunyangNeural","voiceName":"/Users/johnwu/code/anki_experiment/chinese-app-prototype/.data/db/audio/2a0775c1a74478d67dab569114800b9f.mp3","tags":["INVOLVED"]}]}]}