{
  "simplified": "蔬菜",
  "traditional": "蔬菜",
  "pinyin": "shū cài",
  "definitions": [
    {
      "partsOfSpeech": "noun",
      "meaning": "vegetables",
      "sentences": [
        {
          "simplifiedText": "我喜欢吃蔬菜。",
          "traditionalText": "我喜歡吃蔬菜。",
          "pinyin": "Wǒ xǐhuān chī shūcài.",
          "translation": "I like to eat vegetables.",
          "audioPath": "/Users/johnwu/code/anki_experiment/chinese-app-prototype/.data/db/audio/36b0f4b3db88be83d821d7edbd83b509.mp3",
          "voiceName": "zh-CN-XiaoyanNeural",
          "tags": [
            "EASY_TO_USE"
          ]
        },
        {
          "simplifiedText": "健康飲食的一部分是要吃足夠的蔬菜。",
          "traditionalText": "健康飲食的一部分是要吃足夠的蔬菜。",
          "pinyin": "Jiànkāng yǐnshí de yībùfèn shì yào chī zúgòu de shūcài.",
          "translation": "Part of a healthy diet is eating enough vegetables.",
          "audioPath": "zh-CN-XiaoruiNeural",
          "voiceName": "/Users/johnwu/code/anki_experiment/chinese-app-prototype/.data/db/audio/390370b84a0112cb5d1398d2c37b769d.mp3",
          "tags": [
            "INVOLVED"
          ]
        }
      ]
    }
  ]
}